qnsync/__init__.py
qnsync/main.py
qnsync-0.5.dist-info/LICENSE
qnsync-0.5.dist-info/METADATA
qnsync-0.5.dist-info/WHEEL
qnsync-0.5.dist-info/entry_points.txt
qnsync-0.5.dist-info/top_level.txt
qnsync-0.5.dist-info/RECORD
