Metadata-Version: 2.1
Name: qnsync
Version: 0.5
Summary: Sync file to qiniu kodo
Home-page: https://github.com/Gingmzmzx/qnsync
Author: xzyStudio
Author-email: gingmzmzx@gmail.com
License: Apache License 2.0
Platform: UNKNOWN
Requires-Dist: click
